<?xml version="1.0" encoding="utf-8"?>
<TextureAtlas imagePath="impostor.png">
	<!-- Created with Adobe Animate version 23.0.1.70 -->
	<!-- http://www.adobe.com/products/animate.html -->
	<SubTexture name="Impostor Down0000" x="3321" y="2439" width="436" height="439" frameX="-22" frameY="-21" frameWidth="458" frameHeight="461"/>
	<SubTexture name="Impostor Down0001" x="3321" y="2439" width="436" height="439" frameX="-22" frameY="-21" frameWidth="458" frameHeight="461"/>
	<SubTexture name="Impostor Down0002" x="1743" y="1489" width="447" height="457" frameX="-2" frameY="-3" frameWidth="458" frameHeight="461"/>
	<SubTexture name="Impostor Down0003" x="1743" y="1489" width="447" height="457" frameX="-2" frameY="-3" frameWidth="458" frameHeight="461"/>
	<SubTexture name="Impostor Down0004" x="3321" y="1974" width="447" height="461" frameX="0" frameY="0" frameWidth="458" frameHeight="461"/>
	<SubTexture name="Impostor Down0005" x="3321" y="1974" width="447" height="461" frameX="0" frameY="0" frameWidth="458" frameHeight="461"/>
	<SubTexture name="Impostor Down0006" x="3321" y="1974" width="447" height="461" frameX="0" frameY="0" frameWidth="458" frameHeight="461"/>
	<SubTexture name="Impostor Down0007" x="3321" y="1974" width="447" height="461" frameX="0" frameY="0" frameWidth="458" frameHeight="461"/>
	<SubTexture name="Impostor Down0008" x="3321" y="1974" width="447" height="461" frameX="0" frameY="0" frameWidth="458" frameHeight="461"/>
	<SubTexture name="Impostor Down0009" x="3321" y="1974" width="447" height="461" frameX="0" frameY="0" frameWidth="458" frameHeight="461"/>
	<SubTexture name="Impostor Down0010" x="3321" y="1974" width="447" height="461" frameX="0" frameY="0" frameWidth="458" frameHeight="461"/>
	<SubTexture name="Impostor Down0011" x="3321" y="1974" width="447" height="461" frameX="0" frameY="0" frameWidth="458" frameHeight="461"/>
	<SubTexture name="Impostor Down0012" x="3321" y="1974" width="447" height="461" frameX="0" frameY="0" frameWidth="458" frameHeight="461"/>
	<SubTexture name="Impostor Down0013" x="3321" y="1974" width="447" height="461" frameX="0" frameY="0" frameWidth="458" frameHeight="461"/>
	<SubTexture name="Impostor Down0014" x="3321" y="1974" width="447" height="461" frameX="0" frameY="0" frameWidth="458" frameHeight="461"/>
	<SubTexture name="Impostor Idle0000" x="0" y="0" width="682" height="457" frameX="0" frameY="-33" frameWidth="682" frameHeight="490"/>
	<SubTexture name="Impostor Idle0001" x="0" y="0" width="682" height="457" frameX="0" frameY="-33" frameWidth="682" frameHeight="490"/>
	<SubTexture name="Impostor Idle0002" x="686" y="0" width="679" height="454" frameX="-3" frameY="-36" frameWidth="682" frameHeight="490"/>
	<SubTexture name="Impostor Idle0003" x="686" y="0" width="679" height="454" frameX="-3" frameY="-36" frameWidth="682" frameHeight="490"/>
	<SubTexture name="Impostor Idle0004" x="2608" y="0" width="648" height="472" frameX="-7" frameY="-17" frameWidth="682" frameHeight="490"/>
	<SubTexture name="Impostor Idle0005" x="2608" y="0" width="648" height="472" frameX="-7" frameY="-17" frameWidth="682" frameHeight="490"/>
	<SubTexture name="Impostor Idle0006" x="2323" y="1462" width="578" height="487" frameX="-26" frameY="-2" frameWidth="682" frameHeight="490"/>
	<SubTexture name="Impostor Idle0007" x="2323" y="1462" width="578" height="487" frameX="-26" frameY="-2" frameWidth="682" frameHeight="490"/>
	<SubTexture name="Impostor Idle0008" x="0" y="461" width="577" height="489" frameX="-26" frameY="0" frameWidth="682" frameHeight="490"/>
	<SubTexture name="Impostor Idle0009" x="0" y="461" width="577" height="489" frameX="-26" frameY="0" frameWidth="682" frameHeight="490"/>
	<SubTexture name="Impostor Idle0010" x="0" y="461" width="577" height="489" frameX="-26" frameY="0" frameWidth="682" frameHeight="490"/>
	<SubTexture name="Impostor Idle0011" x="0" y="461" width="577" height="489" frameX="-26" frameY="0" frameWidth="682" frameHeight="490"/>
	<SubTexture name="Impostor Idle0012" x="0" y="461" width="577" height="489" frameX="-26" frameY="0" frameWidth="682" frameHeight="490"/>
	<SubTexture name="Impostor Idle0013" x="0" y="461" width="577" height="489" frameX="-26" frameY="0" frameWidth="682" frameHeight="490"/>
	<SubTexture name="Impostor Left0000" x="3260" y="0" width="611" height="496" frameX="0" frameY="-3" frameWidth="623" frameHeight="499"/>
	<SubTexture name="Impostor Left0001" x="3260" y="0" width="611" height="496" frameX="0" frameY="-3" frameWidth="623" frameHeight="499"/>
	<SubTexture name="Impostor Left0002" x="1989" y="0" width="615" height="499" frameX="-7" frameY="0" frameWidth="623" frameHeight="499"/>
	<SubTexture name="Impostor Left0003" x="1989" y="0" width="615" height="499" frameX="-7" frameY="0" frameWidth="623" frameHeight="499"/>
	<SubTexture name="Impostor Left0004" x="1369" y="0" width="616" height="499" frameX="-7" frameY="0" frameWidth="623" frameHeight="499"/>
	<SubTexture name="Impostor Left0005" x="1369" y="0" width="616" height="499" frameX="-7" frameY="0" frameWidth="623" frameHeight="499"/>
	<SubTexture name="Impostor Left0006" x="1369" y="0" width="616" height="499" frameX="-7" frameY="0" frameWidth="623" frameHeight="499"/>
	<SubTexture name="Impostor Left0007" x="1369" y="0" width="616" height="499" frameX="-7" frameY="0" frameWidth="623" frameHeight="499"/>
	<SubTexture name="Impostor Left0008" x="1369" y="0" width="616" height="499" frameX="-7" frameY="0" frameWidth="623" frameHeight="499"/>
	<SubTexture name="Impostor Left0009" x="1369" y="0" width="616" height="499" frameX="-7" frameY="0" frameWidth="623" frameHeight="499"/>
	<SubTexture name="Impostor Left0010" x="1369" y="0" width="616" height="499" frameX="-7" frameY="0" frameWidth="623" frameHeight="499"/>
	<SubTexture name="Impostor Left0011" x="1369" y="0" width="616" height="499" frameX="-7" frameY="0" frameWidth="623" frameHeight="499"/>
	<SubTexture name="Impostor Left0012" x="1369" y="0" width="616" height="499" frameX="-7" frameY="0" frameWidth="623" frameHeight="499"/>
	<SubTexture name="Impostor Left0013" x="1369" y="0" width="616" height="499" frameX="-7" frameY="0" frameWidth="623" frameHeight="499"/>
	<SubTexture name="Impostor Left0014" x="1369" y="0" width="616" height="499" frameX="-7" frameY="0" frameWidth="623" frameHeight="499"/>
	<SubTexture name="Impostor Nah0000" x="0" y="461" width="577" height="489" frameX="-16" frameY="0" frameWidth="682" frameHeight="490"/>
	<SubTexture name="Impostor Nah0001" x="0" y="461" width="577" height="489" frameX="-16" frameY="0" frameWidth="682" frameHeight="490"/>
	<SubTexture name="Impostor Nah0002" x="0" y="461" width="577" height="489" frameX="-16" frameY="0" frameWidth="682" frameHeight="490"/>
	<SubTexture name="Impostor Nah0003" x="1743" y="996" width="576" height="489" frameX="-16" frameY="0" frameWidth="593" frameHeight="489"/>
	<SubTexture name="Impostor Nah0004" x="1743" y="996" width="576" height="489" frameX="-16" frameY="0" frameWidth="593" frameHeight="489"/>
	<SubTexture name="Impostor Nah0005" x="0" y="1447" width="575" height="489" frameX="-13" frameY="0" frameWidth="593" frameHeight="489"/>
	<SubTexture name="Impostor Nah0006" x="0" y="1447" width="575" height="489" frameX="-13" frameY="0" frameWidth="593" frameHeight="489"/>
	<SubTexture name="Impostor Nah0007" x="581" y="1444" width="576" height="489" frameX="-8" frameY="0" frameWidth="593" frameHeight="489"/>
	<SubTexture name="Impostor Nah0008" x="581" y="1444" width="576" height="489" frameX="-8" frameY="0" frameWidth="593" frameHeight="489"/>
	<SubTexture name="Impostor Nah0009" x="3489" y="1486" width="577" height="484" frameX="-4" frameY="-5" frameWidth="593" frameHeight="489"/>
	<SubTexture name="Impostor Nah0010" x="3489" y="1486" width="577" height="484" frameX="-4" frameY="-5" frameWidth="593" frameHeight="489"/>
	<SubTexture name="Impostor Nah0011" x="1161" y="1489" width="578" height="483" frameX="-3" frameY="-6" frameWidth="593" frameHeight="489"/>
	<SubTexture name="Impostor Nah0012" x="1161" y="1489" width="578" height="483" frameX="-3" frameY="-6" frameWidth="593" frameHeight="489"/>
	<SubTexture name="Impostor Nah0013" x="0" y="1940" width="580" height="481" frameX="-1" frameY="-8" frameWidth="593" frameHeight="489"/>
	<SubTexture name="Impostor Nah0014" x="0" y="1940" width="580" height="481" frameX="-1" frameY="-8" frameWidth="593" frameHeight="489"/>
	<SubTexture name="Impostor Nah0015" x="1743" y="1953" width="581" height="480" frameX="0" frameY="-9" frameWidth="593" frameHeight="489"/>
	<SubTexture name="Impostor Nah0016" x="1743" y="1953" width="581" height="480" frameX="0" frameY="-9" frameWidth="593" frameHeight="489"/>
	<SubTexture name="Impostor Nah0017" x="1743" y="1953" width="581" height="480" frameX="0" frameY="-9" frameWidth="593" frameHeight="489"/>
	<SubTexture name="Impostor Nah0018" x="1743" y="1953" width="581" height="480" frameX="0" frameY="-9" frameWidth="593" frameHeight="489"/>
	<SubTexture name="Impostor Nah0019" x="1743" y="1953" width="581" height="480" frameX="0" frameY="-9" frameWidth="593" frameHeight="489"/>
	<SubTexture name="Impostor Nah0020" x="1743" y="1953" width="581" height="480" frameX="0" frameY="-9" frameWidth="593" frameHeight="489"/>
	<SubTexture name="Impostor Nah0021" x="1743" y="1953" width="581" height="480" frameX="0" frameY="-9" frameWidth="593" frameHeight="489"/>
	<SubTexture name="Impostor Nah0022" x="1743" y="1953" width="581" height="480" frameX="0" frameY="-9" frameWidth="593" frameHeight="489"/>
	<SubTexture name="Impostor Nah0023" x="1743" y="1953" width="581" height="480" frameX="0" frameY="-9" frameWidth="593" frameHeight="489"/>
	<SubTexture name="Impostor Nah0024" x="1743" y="1953" width="581" height="480" frameX="0" frameY="-9" frameWidth="593" frameHeight="489"/>
	<SubTexture name="Impostor Nah0025" x="1743" y="1953" width="581" height="480" frameX="0" frameY="-9" frameWidth="593" frameHeight="489"/>
	<SubTexture name="Impostor Nah0026" x="1743" y="1953" width="581" height="480" frameX="0" frameY="-9" frameWidth="593" frameHeight="489"/>
	<SubTexture name="Impostor Nah0027" x="1743" y="1953" width="581" height="480" frameX="0" frameY="-9" frameWidth="593" frameHeight="489"/>
	<SubTexture name="Impostor Nah0028" x="1743" y="1953" width="581" height="480" frameX="0" frameY="-9" frameWidth="593" frameHeight="489"/>
	<SubTexture name="Impostor Nah0029" x="1743" y="1953" width="581" height="480" frameX="0" frameY="-9" frameWidth="593" frameHeight="489"/>
	<SubTexture name="Impostor Nah0030" x="1743" y="1953" width="581" height="480" frameX="0" frameY="-9" frameWidth="593" frameHeight="489"/>
	<SubTexture name="Impostor Nah0031" x="1743" y="1953" width="581" height="480" frameX="0" frameY="-9" frameWidth="593" frameHeight="489"/>
	<SubTexture name="Impostor Nah0032" x="1743" y="1953" width="581" height="480" frameX="0" frameY="-9" frameWidth="593" frameHeight="489"/>
	<SubTexture name="Impostor Nah0033" x="1743" y="1953" width="581" height="480" frameX="0" frameY="-9" frameWidth="593" frameHeight="489"/>
	<SubTexture name="Impostor Nah0034" x="1743" y="1953" width="581" height="480" frameX="0" frameY="-9" frameWidth="593" frameHeight="489"/>
	<SubTexture name="Impostor Nah0035" x="2905" y="1486" width="580" height="482" frameX="-2" frameY="-7" frameWidth="593" frameHeight="489"/>
	<SubTexture name="Impostor Nah0036" x="2905" y="1486" width="580" height="482" frameX="-2" frameY="-7" frameWidth="593" frameHeight="489"/>
	<SubTexture name="Impostor Nah0037" x="686" y="458" width="578" height="489" frameX="-15" frameY="0" frameWidth="593" frameHeight="489"/>
	<SubTexture name="Impostor Nah0038" x="686" y="458" width="578" height="489" frameX="-15" frameY="0" frameWidth="593" frameHeight="489"/>
	<SubTexture name="Impostor Nah0039" x="0" y="461" width="577" height="489" frameX="-16" frameY="0" frameWidth="682" frameHeight="490"/>
	<SubTexture name="Impostor Nah0040" x="2608" y="476" width="577" height="489" frameX="-16" frameY="0" frameWidth="593" frameHeight="489"/>
	<SubTexture name="Impostor Nah0041" x="3189" y="500" width="577" height="489" frameX="-16" frameY="0" frameWidth="593" frameHeight="489"/>
	<SubTexture name="Impostor Nah0042" x="1268" y="503" width="577" height="489" frameX="-16" frameY="0" frameWidth="593" frameHeight="489"/>
	<SubTexture name="Impostor Nah0043" x="1849" y="503" width="577" height="489" frameX="-16" frameY="0" frameWidth="593" frameHeight="489"/>
	<SubTexture name="Impostor Nah0044" x="581" y="951" width="577" height="489" frameX="-16" frameY="0" frameWidth="593" frameHeight="489"/>
	<SubTexture name="Impostor Nah0045" x="0" y="954" width="577" height="489" frameX="-16" frameY="0" frameWidth="593" frameHeight="489"/>
	<SubTexture name="Impostor Nah0046" x="2430" y="969" width="577" height="489" frameX="-16" frameY="0" frameWidth="593" frameHeight="489"/>
	<SubTexture name="Impostor Nah0047" x="2430" y="969" width="577" height="489" frameX="-16" frameY="0" frameWidth="593" frameHeight="489"/>
	<SubTexture name="Impostor Nah0048" x="3011" y="993" width="577" height="489" frameX="-16" frameY="0" frameWidth="593" frameHeight="489"/>
	<SubTexture name="Impostor Nah0049" x="3011" y="993" width="577" height="489" frameX="-16" frameY="0" frameWidth="593" frameHeight="489"/>
	<SubTexture name="Impostor Nah0050" x="1162" y="996" width="577" height="489" frameX="-16" frameY="0" frameWidth="593" frameHeight="489"/>
	<SubTexture name="Impostor Nah0051" x="1162" y="996" width="577" height="489" frameX="-16" frameY="0" frameWidth="593" frameHeight="489"/>
	<SubTexture name="Impostor Nah0052" x="1162" y="996" width="577" height="489" frameX="-16" frameY="0" frameWidth="593" frameHeight="489"/>
	<SubTexture name="Impostor Nah0053" x="1162" y="996" width="577" height="489" frameX="-16" frameY="0" frameWidth="593" frameHeight="489"/>
	<SubTexture name="Impostor Nah0054" x="1162" y="996" width="577" height="489" frameX="-16" frameY="0" frameWidth="593" frameHeight="489"/>
	<SubTexture name="Impostor Nah0055" x="1162" y="996" width="577" height="489" frameX="-16" frameY="0" frameWidth="593" frameHeight="489"/>
	<SubTexture name="Impostor Nah0056" x="1162" y="996" width="577" height="489" frameX="-16" frameY="0" frameWidth="593" frameHeight="489"/>
	<SubTexture name="Impostor Nah0057" x="1162" y="996" width="577" height="489" frameX="-16" frameY="0" frameWidth="593" frameHeight="489"/>
	<SubTexture name="Impostor Nah0058" x="1162" y="996" width="577" height="489" frameX="-16" frameY="0" frameWidth="593" frameHeight="489"/>
	<SubTexture name="Impostor Nah0059" x="1162" y="996" width="577" height="489" frameX="-16" frameY="0" frameWidth="593" frameHeight="489"/>
	<SubTexture name="Impostor Nah0060" x="1162" y="996" width="577" height="489" frameX="-16" frameY="0" frameWidth="593" frameHeight="489"/>
	<SubTexture name="Impostor Nah0061" x="1162" y="996" width="577" height="489" frameX="-16" frameY="0" frameWidth="593" frameHeight="489"/>
	<SubTexture name="Impostor Nah0062" x="1162" y="996" width="577" height="489" frameX="-16" frameY="0" frameWidth="593" frameHeight="489"/>
	<SubTexture name="Impostor Nah0063" x="1162" y="996" width="577" height="489" frameX="-16" frameY="0" frameWidth="593" frameHeight="489"/>
	<SubTexture name="Impostor Nah0064" x="1162" y="996" width="577" height="489" frameX="-16" frameY="0" frameWidth="593" frameHeight="489"/>
	<SubTexture name="Impostor Nah0065" x="1162" y="996" width="577" height="489" frameX="-16" frameY="0" frameWidth="593" frameHeight="489"/>
	<SubTexture name="Impostor Nah0066" x="1162" y="996" width="577" height="489" frameX="-16" frameY="0" frameWidth="593" frameHeight="489"/>
	<SubTexture name="Impostor Nah0067" x="1162" y="996" width="577" height="489" frameX="-16" frameY="0" frameWidth="593" frameHeight="489"/>
	<SubTexture name="Impostor Nah0068" x="1162" y="996" width="577" height="489" frameX="-16" frameY="0" frameWidth="593" frameHeight="489"/>
	<SubTexture name="Impostor Nah0069" x="1162" y="996" width="577" height="489" frameX="-16" frameY="0" frameWidth="593" frameHeight="489"/>
	<SubTexture name="Impostor Nah0070" x="1162" y="996" width="577" height="489" frameX="-16" frameY="0" frameWidth="593" frameHeight="489"/>
	<SubTexture name="Impostor Nah0071" x="1162" y="996" width="577" height="489" frameX="-16" frameY="0" frameWidth="593" frameHeight="489"/>
	<SubTexture name="Impostor Nah0072" x="1162" y="996" width="577" height="489" frameX="-16" frameY="0" frameWidth="593" frameHeight="489"/>
	<SubTexture name="Impostor Nah0073" x="1162" y="996" width="577" height="489" frameX="-16" frameY="0" frameWidth="593" frameHeight="489"/>
	<SubTexture name="Impostor Right0000" x="3592" y="993" width="426" height="488" frameX="-7" frameY="0" frameWidth="433" frameHeight="488"/>
	<SubTexture name="Impostor Right0001" x="3592" y="993" width="426" height="488" frameX="-7" frameY="0" frameWidth="433" frameHeight="488"/>
	<SubTexture name="Impostor Right0002" x="1104" y="1976" width="401" height="486" frameX="-2" frameY="-2" frameWidth="433" frameHeight="488"/>
	<SubTexture name="Impostor Right0003" x="1104" y="1976" width="401" height="486" frameX="-2" frameY="-2" frameWidth="433" frameHeight="488"/>
	<SubTexture name="Impostor Right0004" x="1509" y="2437" width="396" height="484" frameX="-1" frameY="-4" frameWidth="433" frameHeight="488"/>
	<SubTexture name="Impostor Right0005" x="1509" y="2437" width="396" height="484" frameX="-1" frameY="-4" frameWidth="433" frameHeight="488"/>
	<SubTexture name="Impostor Right0006" x="0" y="2425" width="397" height="484" frameX="0" frameY="-4" frameWidth="433" frameHeight="488"/>
	<SubTexture name="Impostor Right0007" x="0" y="2425" width="397" height="484" frameX="0" frameY="-4" frameWidth="433" frameHeight="488"/>
	<SubTexture name="Impostor Right0008" x="0" y="2425" width="397" height="484" frameX="0" frameY="-4" frameWidth="433" frameHeight="488"/>
	<SubTexture name="Impostor Right0009" x="0" y="2425" width="397" height="484" frameX="0" frameY="-4" frameWidth="433" frameHeight="488"/>
	<SubTexture name="Impostor Right0010" x="0" y="2425" width="397" height="484" frameX="0" frameY="-4" frameWidth="433" frameHeight="488"/>
	<SubTexture name="Impostor Right0011" x="0" y="2425" width="397" height="484" frameX="0" frameY="-4" frameWidth="433" frameHeight="488"/>
	<SubTexture name="Impostor Right0012" x="0" y="2425" width="397" height="484" frameX="0" frameY="-4" frameWidth="433" frameHeight="488"/>
	<SubTexture name="Impostor Up0000" x="2841" y="1972" width="476" height="509" frameX="-9" frameY="0" frameWidth="516" frameHeight="509"/>
	<SubTexture name="Impostor Up0001" x="2841" y="1972" width="476" height="509" frameX="-9" frameY="0" frameWidth="516" frameHeight="509"/>
	<SubTexture name="Impostor Up0002" x="2328" y="1953" width="509" height="504" frameX="-4" frameY="0" frameWidth="516" frameHeight="509"/>
	<SubTexture name="Impostor Up0003" x="2328" y="1953" width="509" height="504" frameX="-4" frameY="0" frameWidth="516" frameHeight="509"/>
	<SubTexture name="Impostor Up0004" x="584" y="1937" width="516" height="500" frameX="0" frameY="-1" frameWidth="516" frameHeight="509"/>
	<SubTexture name="Impostor Up0005" x="584" y="1937" width="516" height="500" frameX="0" frameY="-1" frameWidth="516" frameHeight="509"/>
	<SubTexture name="Impostor Up0006" x="584" y="1937" width="516" height="500" frameX="0" frameY="-1" frameWidth="516" frameHeight="509"/>
	<SubTexture name="Impostor Up0007" x="584" y="1937" width="516" height="500" frameX="0" frameY="-1" frameWidth="516" frameHeight="509"/>
	<SubTexture name="Impostor Up0008" x="584" y="1937" width="516" height="500" frameX="0" frameY="-1" frameWidth="516" frameHeight="509"/>
	<SubTexture name="Impostor Up0009" x="584" y="1937" width="516" height="500" frameX="0" frameY="-1" frameWidth="516" frameHeight="509"/>
	<SubTexture name="Impostor Up0010" x="584" y="1937" width="516" height="500" frameX="0" frameY="-1" frameWidth="516" frameHeight="509"/>
	<SubTexture name="Impostor Up0011" x="584" y="1937" width="516" height="500" frameX="0" frameY="-1" frameWidth="516" frameHeight="509"/>
	<SubTexture name="Impostor Up0012" x="584" y="1937" width="516" height="500" frameX="0" frameY="-1" frameWidth="516" frameHeight="509"/>
	<SubTexture name="Impostor Up0013" x="584" y="1937" width="516" height="500" frameX="0" frameY="-1" frameWidth="516" frameHeight="509"/>
</TextureAtlas>
